MANIFEST.in
setup.py
toxicjasmine/README
toxicjasmine/__init__.py
toxicjasmine/boot.js
toxicjasmine/jasmine-clear.css
toxicjasmine/jasmine-dark.css
toxicjasmine/jasmine-html.js
toxicjasmine/jasmine.css
toxicjasmine/jasmine.js
toxicjasmine/json2.js
toxicjasmine/monkey.py
toxicjasmine/node_boot.js
toxicjasmine.egg-info/PKG-INFO
toxicjasmine.egg-info/SOURCES.txt
toxicjasmine.egg-info/dependency_links.txt
toxicjasmine.egg-info/entry_points.txt
toxicjasmine.egg-info/requires.txt
toxicjasmine.egg-info/top_level.txt